{
  "id": "pdlc-2026-06-19-gateway-docker",
  "feature": "Docker image for @bolyra/gateway with GHCR publishing and CI workflow",
  "status": "active",
  "stage": "IMPLEMENT",
  "mode": "standard",
  "created": "2026-06-19T00:00:00Z",
  "updated": "2026-06-19T12:00:00Z",
  "spec": "docs/superpowers/specs/2026-06-19-gateway-docker-design.md",
  "plan": "docs/superpowers/plans/2026-06-19-gateway-docker.md",
  "gates": {
    "spec": { "status": "approved" },
    "plan": { "status": "approved" },
    "ship": { "status": "pending" },
    "post_ship": { "status": "pending" }
  },
  "tasks": [
    {
      "id": 1,
      "description": "Create Dockerfile.gateway at repo root with multi-stage build installing @bolyra/gateway from npm",
      "type": "parallel",
      "depends_on": [],
      "status": "in_progress",
      "input_files": ["integrations/gateway/package.json"],
      "output_files": ["Dockerfile.gateway"],
      "test_command": "docker build -f Dockerfile.gateway -t bolyra-gateway-test .",
      "test_expectation": "Image builds successfully"
    },
    {
      "id": 2,
      "description": "Create .dockerignore at repo root to minimize build context",
      "type": "parallel",
      "depends_on": [],
      "status": "in_progress",
      "input_files": [],
      "output_files": [".dockerignore"],
      "test_command": null,
      "test_expectation": "File exists with proper exclusions"
    },
    {
      "id": 3,
      "description": "Create GitHub Actions workflow for Docker build and GHCR push",
      "type": "parallel",
      "depends_on": [],
      "status": "in_progress",
      "input_files": [".github/workflows/ci.yml"],
      "output_files": [".github/workflows/docker-gateway.yml"],
      "test_command": null,
      "test_expectation": "Valid YAML workflow with correct triggers and steps"
    },
    {
      "id": 4,
      "description": "Update integrations/gateway/README.md with Docker usage section",
      "type": "parallel",
      "depends_on": [],
      "status": "in_progress",
      "input_files": ["integrations/gateway/README.md"],
      "output_files": ["integrations/gateway/README.md"],
      "test_command": null,
      "test_expectation": "Docker section added with build, run, and healthcheck examples"
    },
    {
      "id": 5,
      "description": "Build and smoke-test Docker image locally",
      "type": "sequential",
      "depends_on": [1, 2],
      "status": "pending",
      "input_files": ["Dockerfile.gateway", ".dockerignore"],
      "output_files": [],
      "test_command": "docker build -f Dockerfile.gateway -t bolyra-gateway-test . && docker run --rm -d -p 4100:4100 --name bolyra-gw-test bolyra-gateway-test --target http://host.docker.internal:3000/mcp --dev && sleep 3 && curl -s http://localhost:4100/healthz && docker stop bolyra-gw-test",
      "test_expectation": "Build succeeds, container starts, /healthz returns 200"
    }
  ],
  "reviews": {},
  "release": {}
}
