{
  "id": "cross_chain_engineer_storage_proof_root_sync",
  "persona": "cross_chain_engineer",
  "title": "Cross-chain Merkle root sync via EIP-1186 storage proofs",
  "dimension": "completeness",
  "description": "Deploy IdentityRegistry on Arbitrum and Polygon alongside Base Sepolia, then implement a RootRelay contract that accepts EIP-1186 storage proofs to sync humanTree and agentTree roots across chains without a trusted relayer. The source chain's root slot is proven against a block hash anchored by each L2's native L1 state oracle (Arbitrum's ArbSys, Polygon's StateSender). This eliminates the single-chain bottleneck where agents on Arbitrum cannot verify credentials enrolled on Base.",
  "priority": "high",
  "estimated_effort": "days",
  "candidate_id": "cross_chain_engineer_storage_proof_root_sync",
  "adoption": 18,
  "standards": 18,
  "completeness": 22,
  "correctness": 15,
  "total": 73,
  "verdict": "consider"
}